CHANGES.rst
LICENSE.GPL
LICENSE.rst
MANIFEST.in
README.rst
setup.cfg
setup.py
src/collective/__init__.py
src/collective.multilingual.egg-info/PKG-INFO
src/collective.multilingual.egg-info/SOURCES.txt
src/collective.multilingual.egg-info/dependency_links.txt
src/collective.multilingual.egg-info/entry_points.txt
src/collective.multilingual.egg-info/namespace_packages.txt
src/collective.multilingual.egg-info/not-zip-safe
src/collective.multilingual.egg-info/requires.txt
src/collective.multilingual.egg-info/top_level.txt
src/collective/multilingual/__init__.py
src/collective/multilingual/catalog.py
src/collective/multilingual/configure.zcml
src/collective/multilingual/events.py
src/collective/multilingual/graph.py
src/collective/multilingual/i18n.py
src/collective/multilingual/interfaces.py
src/collective/multilingual/patches.py
src/collective/multilingual/query.py
src/collective/multilingual/setuphandlers.py
src/collective/multilingual/testing.py
src/collective/multilingual/utils.py
src/collective/multilingual/vocabularies.py
src/collective/multilingual/browser/__init__.py
src/collective/multilingual/browser/configure.zcml
src/collective/multilingual/browser/controlpanel.py
src/collective/multilingual/browser/form.py
src/collective/multilingual/browser/languages.py
src/collective/multilingual/browser/menu.py
src/collective/multilingual/browser/notices.py
src/collective/multilingual/browser/setup.py
src/collective/multilingual/browser/resources/icon.png
src/collective/multilingual/browser/templates/control-panel.pt
src/collective/multilingual/browser/templates/languages-notice.pt
src/collective/multilingual/browser/templates/languageselector.pt
src/collective/multilingual/browser/templates/parent-not-translated-notice.pt
src/collective/multilingual/locales/collective.multilingual.pot
src/collective/multilingual/locales/da/LC_MESSAGES/collective.multilingual.mo
src/collective/multilingual/locales/da/LC_MESSAGES/collective.multilingual.po
src/collective/multilingual/profiles/default/browserlayer.xml
src/collective/multilingual/profiles/default/catalog.xml
src/collective/multilingual/profiles/default/controlpanel.xml
src/collective/multilingual/profiles/default/metadata.xml
src/collective/multilingual/profiles/default/registry.xml
src/collective/multilingual/profiles/uninstall/browserlayer.xml
src/collective/multilingual/profiles/uninstall/catalog.xml
