Metadata-Version: 2.1
Name: collective.multilingual
Version: 2.0
Summary: Create, relate and manage content in multiple languages in Plone!
Author: Malthe Borch
Author-email: mborch@gmail.com
License: GPL version 2
Keywords: plone multilingual dexterity
Classifier: Environment :: Web Environment
Classifier: Framework :: Plone
Classifier: Framework :: Plone :: Addon
Classifier: Framework :: Plone :: 5.2
Classifier: Programming Language :: Python
Classifier: Programming Language :: Python :: 3.7
Classifier: Programming Language :: Python :: 3.8
Classifier: Programming Language :: Python :: 3.9
Classifier: Programming Language :: Python :: 3.10
Classifier: Operating System :: OS Independent
Classifier: License :: OSI Approved :: GNU General Public License v2 (GPLv2)
Requires-Python: >=2.7,!=3.6.*,<=4.0
Provides-Extra: test
License-File: LICENSE.GPL
License-File: LICENSE.rst
